surface_spaces/__init__.py
surface_spaces/data/aparc.a2009s/meta.npz
surface_spaces/data/aparc.a2009s/fsavg-ico128/on1031/lh_trimmed_parc.npy
surface_spaces/data/aparc.a2009s/fsavg-ico128/on1031/rh_trimmed_parc.npy
surface_spaces/data/aparc.a2009s/fsavg-ico32/on1031/lh_trimmed_parc.npy
surface_spaces/data/aparc.a2009s/fsavg-ico32/on1031/rh_trimmed_parc.npy
surface_spaces/data/aparc.a2009s/fsavg-ico64/on1031/lh_trimmed_parc.npy
surface_spaces/data/aparc.a2009s/fsavg-ico64/on1031/rh_trimmed_parc.npy
surface_spaces/data/aparc.a2009s/onavg-ico128/on1031/lh_trimmed_parc.npy
surface_spaces/data/aparc.a2009s/onavg-ico128/on1031/rh_trimmed_parc.npy
surface_spaces/data/aparc.a2009s/onavg-ico32/on1031/lh_trimmed_parc.npy
surface_spaces/data/aparc.a2009s/onavg-ico32/on1031/rh_trimmed_parc.npy
surface_spaces/data/aparc.a2009s/onavg-ico64/on1031/lh_trimmed_parc.npy
surface_spaces/data/aparc.a2009s/onavg-ico64/on1031/rh_trimmed_parc.npy
surface_spaces/data/cortical_masks/fsavg-ico128/fsavg/lh.npy
surface_spaces/data/cortical_masks/fsavg-ico128/fsavg/rh.npy
surface_spaces/data/cortical_masks/fsavg-ico128/fsavg5/lh.npy
surface_spaces/data/cortical_masks/fsavg-ico128/fsavg5/rh.npy
surface_spaces/data/cortical_masks/fsavg-ico128/fsavg6/lh.npy
surface_spaces/data/cortical_masks/fsavg-ico128/fsavg6/rh.npy
surface_spaces/data/cortical_masks/fsavg-ico128/on1031/lh.npy
surface_spaces/data/cortical_masks/fsavg-ico128/on1031/rh.npy
surface_spaces/data/cortical_masks/fsavg-ico32/fsavg/lh.npy
surface_spaces/data/cortical_masks/fsavg-ico32/fsavg/rh.npy
surface_spaces/data/cortical_masks/fsavg-ico32/fsavg5/lh.npy
surface_spaces/data/cortical_masks/fsavg-ico32/fsavg5/rh.npy
surface_spaces/data/cortical_masks/fsavg-ico32/fsavg6/lh.npy
surface_spaces/data/cortical_masks/fsavg-ico32/fsavg6/rh.npy
surface_spaces/data/cortical_masks/fsavg-ico32/on1031/lh.npy
surface_spaces/data/cortical_masks/fsavg-ico32/on1031/rh.npy
surface_spaces/data/cortical_masks/fsavg-ico64/fsavg/lh.npy
surface_spaces-0.1.0.dist-info/LICENSE
surface_spaces-0.1.0.dist-info/METADATA
surface_spaces-0.1.0.dist-info/WHEEL
surface_spaces-0.1.0.dist-info/top_level.txt
surface_spaces-0.1.0.dist-info/RECORD
