Metadata-Version: 2.1
Name: surface-spaces
Version: 0.1.0
Summary: Convenient conversion between surface spaces.
Home-page: https://feilong.github.io/surface_spaces/
Author: Ma Feilong
Author-email: mafeilong@gmail.com
Project-URL: Bug Tracker, https://github.com/feilong/surface_spaces/issues
Project-URL: Source Code, https://github.com/feilong/surface_spaces
Keywords: brain,surface,cortex,fmri,neuroimaging
Classifier: Programming Language :: Python :: 3 :: Only
Classifier: Programming Language :: Python :: 3.6
Classifier: Programming Language :: Python :: 3.7
Classifier: Programming Language :: Python :: 3.8
Classifier: Programming Language :: Python :: 3.9
Classifier: Programming Language :: Python :: 3.10
Requires-Python: >=3.6
License-File: LICENSE
Requires-Dist: numpy
Provides-Extra: tests
Requires-Dist: pytest ; extra == 'tests'
